diffsim/__init__.py
diffsim/diffsim.py
diffsim/diffsim_cpu_kernels.py
diffsim/diffsim_gpu_kernels.py
diffsim/diffsim_mpi_kernels.py
diffsim/examples/__init__.py
diffsim/examples/makediff_BTO.py
diffsim/examples/makediff_ZnO.py
diffsim-1.2.dist-info/LICENSE
diffsim-1.2.dist-info/METADATA
diffsim-1.2.dist-info/WHEEL
diffsim-1.2.dist-info/top_level.txt
diffsim-1.2.dist-info/RECORD
