Metadata-Version: 2.1
Name: diffsim
Version: 1.2
Summary: Calculate diffraction patterns from first principles
Author-email: Marcus Newton <Bonsu.Devel@gmail.com>
License: GNU GENERAL PUBLIC LICENSE
Project-URL: Homepage, https://github.com/bonsudev/diffsim
Project-URL: Bug Tracker, https://github.com/bonsudev/diffsim/issues
Classifier: Programming Language :: Python :: 3
Classifier: License :: OSI Approved :: GNU General Public License v3 (GPLv3)
Classifier: Operating System :: OS Independent
Classifier: Environment :: GPU :: NVIDIA CUDA
Classifier: Topic :: Scientific/Engineering :: Physics
Requires-Python: >=3.7
License-File: LICENSE
